README.md
setup.py
tfrecordutils/TFRecordUtils.py
tfrecordutils/__init__.py
tfrecordutils.egg-info/PKG-INFO
tfrecordutils.egg-info/SOURCES.txt
tfrecordutils.egg-info/dependency_links.txt
tfrecordutils.egg-info/top_level.txt