Metadata-Version: 1.1
Name: tfrecordutils
Version: 0.1.4
Summary: Utilities to simplify working with TFRecord files and TensorFlow's data pipeline API
Home-page: https://github.com/mindlapse/tfrecordutils
Author: Dave MacDonald
Author-email: dave@torontoai.org
License: UNKNOWN
Platform: UNKNOWN
Classifier: Programming Language :: Python :: 3
Classifier: License :: OSI Approved :: MIT License
Classifier: Operating System :: OS Independent
